pyprecag/__init__.py
pyprecag/_compat.py
pyprecag/bandops.py
pyprecag/config.json
pyprecag/config.py
pyprecag/convert.py
pyprecag/crs.py
pyprecag/describe.py
pyprecag/errors.py
pyprecag/kriging_ops.py
pyprecag/processing.py
pyprecag/proj.db
pyprecag/raster_ops.py
pyprecag/table_ops.py
pyprecag/vector_ops.py
pyprecag-0.4.3.dist-info/AUTHORS.rst
pyprecag-0.4.3.dist-info/LICENSE
pyprecag-0.4.3.dist-info/METADATA
pyprecag-0.4.3.dist-info/WHEEL
pyprecag-0.4.3.dist-info/top_level.txt
pyprecag-0.4.3.dist-info/RECORD
