Metadata-Version: 2.2
Name: pyprecag
Version: 0.4.3
Summary: A suite of tools for Precision Agriculture
Author-email: Christina Ratcliff <pat@csiro.au>
License: BSD-3-Clause
Project-URL: Homepage, https://github.com/CSIRO-Precision-Agriculture/pyprecag
Keywords: Agriculture,Precision Agriculture,GIS,cartography,geopandas,rasterio
Classifier: Development Status :: 5 - Production/Stable
Classifier: Intended Audience :: Science/Research
Classifier: License :: OSI Approved :: BSD License
Classifier: Programming Language :: Python :: 3
Requires-Python: >=3.8
License-File: LICENSE
License-File: AUTHORS.rst
Requires-Dist: chardet
Requires-Dist: fiona
Requires-Dist: future
Requires-Dist: gdal
Requires-Dist: geopandas
Requires-Dist: matplotlib
Requires-Dist: pyproj
Requires-Dist: rasterio
Requires-Dist: scipy
Requires-Dist: six>1.12.0
Requires-Dist: unidecode
Provides-Extra: dev
Requires-Dist: bump-my-version; extra == "dev"
Requires-Dist: check-manifest; extra == "dev"
Requires-Dist: ipdb; extra == "dev"
Requires-Dist: ipython; extra == "dev"
Requires-Dist: pylint; extra == "dev"
Requires-Dist: pypandoc; extra == "dev"
Requires-Dist: readme_renderer; extra == "dev"
Requires-Dist: setuptools; extra == "dev"
Requires-Dist: sphinx; extra == "dev"
Requires-Dist: sphinx_rtd_theme; extra == "dev"
Requires-Dist: twine; extra == "dev"
Requires-Dist: wheel; extra == "dev"
Provides-Extra: test
Requires-Dist: pylint; extra == "test"
Requires-Dist: tox; extra == "test"
